poczta_polska_enadawca/__init__.py
poczta_polska_enadawca/api.py
poczta_polska_enadawca/settings.py
poczta_polska_enadawca/ws_tracking_api.py
poczta_polska_enadawca-0.8.dist-info/AUTHORS
poczta_polska_enadawca-0.8.dist-info/LICENSE
poczta_polska_enadawca-0.8.dist-info/METADATA
poczta_polska_enadawca-0.8.dist-info/WHEEL
poczta_polska_enadawca-0.8.dist-info/top_level.txt
poczta_polska_enadawca-0.8.dist-info/zip-safe
poczta_polska_enadawca-0.8.dist-info/RECORD
