Metadata-Version: 2.1
Name: poczta-polska-enadawca
Version: 0.8
Summary: Client wrapper for Poczta Polska e-nadawca WSDL API.
Home-page: https://github.com/haloween/poczta-polska-e-nadawca-python
Author: Tomasz Utracki-Janeta
Author-email: halgravity+githubrepo@gmail.com
License: MIT
Keywords: poczta,polska,e-nadawca,enadawca,wsdl,api
Platform: UNKNOWN
Classifier: Development Status :: 4 - Beta
Classifier: Framework :: Django
Classifier: Intended Audience :: Developers
Classifier: License :: OSI Approved :: MIT License
Classifier: Programming Language :: Python :: 3.4
Classifier: Programming Language :: Python :: 3.5
Classifier: Programming Language :: Python :: 3.6
Classifier: Programming Language :: Python :: 3.7
Classifier: Programming Language :: Python :: 3.8
Classifier: Programming Language :: Python :: 3.9
Classifier: Programming Language :: Python :: 3.10
Classifier: Programming Language :: Python :: 3.11
License-File: LICENSE
License-File: AUTHORS
Requires-Dist: zeep
Requires-Dist: requests
